pymodaq_plugins_bnc/__init__.py
pymodaq_plugins_bnc/utils.py
pymodaq_plugins_bnc/daq_move_plugins/__init__.py
pymodaq_plugins_bnc/daq_move_plugins/daq_move_bnc.py
pymodaq_plugins_bnc/daq_viewer_plugins/__init__.py
pymodaq_plugins_bnc/daq_viewer_plugins/plugins_0D/__init__.py
pymodaq_plugins_bnc/daq_viewer_plugins/plugins_1D/__init__.py
pymodaq_plugins_bnc/daq_viewer_plugins/plugins_2D/__init__.py
pymodaq_plugins_bnc/daq_viewer_plugins/plugins_ND/__init__.py
pymodaq_plugins_bnc/exporters/__init__.py
pymodaq_plugins_bnc/extensions/__init__.py
pymodaq_plugins_bnc/hardware/__init__.py
pymodaq_plugins_bnc/hardware/bnc_commands.py
pymodaq_plugins_bnc/hardware/device.py
pymodaq_plugins_bnc/models/__init__.py
pymodaq_plugins_bnc/resources/VERSION
pymodaq_plugins_bnc/resources/__init__.py
pymodaq_plugins_bnc/resources/config_template.toml
pymodaq_plugins_bnc/scanners/__init__.py
pymodaq_plugins_bnc-0.0.10.dist-info/LICENSE
pymodaq_plugins_bnc-0.0.10.dist-info/METADATA
pymodaq_plugins_bnc-0.0.10.dist-info/WHEEL
pymodaq_plugins_bnc-0.0.10.dist-info/entry_points.txt
pymodaq_plugins_bnc-0.0.10.dist-info/top_level.txt
pymodaq_plugins_bnc-0.0.10.dist-info/RECORD
